babbelfish/__init__.py
babbelfish/config.py
babbelfish/py.typed
babbelfish/service.py
babbelfish-0.1.1.dist-info/METADATA
babbelfish-0.1.1.dist-info/WHEEL
babbelfish-0.1.1.dist-info/licenses/LICENSE
babbelfish-0.1.1.dist-info/RECORD
