Metadata-Version: 2.4
Name: babbelfish
Version: 0.1.1
Summary: A framework for lightweight services
Author-email: Aljoscha Sander <aljoscha@flucto.tech>, Felix Weiler-Detjen <felix@flucto.tech>
License: MIT License
License-File: LICENSE
Requires-Python: >=3.10
Requires-Dist: heisskleber>=1.1.0
